CHANGELOG.md
README.md
mitol/__init__.py
mitol/oauth_toolkit_extensions/__init__.py
mitol/oauth_toolkit_extensions/admin.py
mitol/oauth_toolkit_extensions/apps.py
mitol/oauth_toolkit_extensions/backends.py
mitol/oauth_toolkit_extensions/factories.py
mitol/oauth_toolkit_extensions/models.py
mitol/oauth_toolkit_extensions/py.typed
mitol/oauth_toolkit_extensions/utils.py
mitol/oauth_toolkit_extensions/migrations/0001_add_application_access.py
mitol/oauth_toolkit_extensions/migrations/__init__.py
mitol_django_oauth_toolkit_extensions-2025.3.17.dist-info/METADATA
mitol_django_oauth_toolkit_extensions-2025.3.17.dist-info/WHEEL
mitol_django_oauth_toolkit_extensions-2025.3.17.dist-info/RECORD
