Metadata-Version: 2.4
Name: mitol-django-oauth-toolkit-extensions
Version: 2025.3.17
Summary: MIT Open Learning django app extensions for oauth toolkit
License-Expression: BSD-3-Clause
Requires-Python: >=3.10
Requires-Dist: django-oauth-toolkit>=1.3.3
Requires-Dist: django-stubs>=1.13.1
Requires-Dist: django>=3.0
Requires-Dist: factory-boy~=3.2
Requires-Dist: mitol-django-common
Requires-Dist: pytz>=2020.4
Requires-Dist: requests>=2.20.0
